{
  "_class": "group",
  "do_objectID": "B734C718-B4B7-4928-B75A-905885D5C1AA",
  "exportOptions": {
    "_class": "exportOptions",
    "exportFormats": [
    ],
    "includedLayerIds": [
    ],
    "layerOptions": 0,
    "shouldTrim": false
  },
  "frame": {
    "_class": "rect",
    "constrainProportions": false,
    "height": 440,
    "width": 256,
    "x": 0,
    "y": 0
  },
  "hasClickThrough": false,
  "isFlippedHorizontal": false,
  "isFlippedVertical": false,
  "isLocked": false,
  "isVisible": true,
  "layerListExpandedType": 0,
  "layers": [
    {
      "class": "group",
      "id": "7AA98B51-09BC-4A00-9843-82B98B3C891E"
    },
    {
      "class": "group",
      "id": "497763FF-6037-403F-B9A7-64D599C4A468"
    }
  ],
  "name": "default",
  "nameIsFixed": true,
  "originalObjectID": "B734C718-B4B7-4928-B75A-905885D5C1AA",
  "resizingConstraint": 63,
  "resizingType": 0,
  "rotation": 0,
  "shouldBreakMaskChain": false,
  "style": {
    "_class": "style",
    "endDecorationType": 0,
    "miterLimit": 10,
    "shadows": [
      {
        "_class": "shadow",
        "blurRadius": 10,
        "color": {
          "_class": "color",
          "alpha": 0.05,
          "blue": 0,
          "green": 0,
          "red": 0
        },
        "contextSettings": {
          "_class": "graphicsContextSettings",
          "blendMode": 0,
          "opacity": 1
        },
        "isEnabled": true,
        "offsetX": 2,
        "offsetY": 2,
        "spread": 0
      }
    ],
    "startDecorationType": 0
  },
  "userInfo": {
    "com.animaapp.stc-sketch-plugin": {
      "kModelPropertiesKey": {
      }
    }
  }
}