{
  "_class": "group",
  "do_objectID": "477A84F2-CBF3-443B-A824-6C16811267A7",
  "exportOptions": {
    "_class": "exportOptions",
    "exportFormats": [
    ],
    "includedLayerIds": [
    ],
    "layerOptions": 0,
    "shouldTrim": false
  },
  "frame": {
    "_class": "rect",
    "constrainProportions": false,
    "height": 16,
    "width": 103,
    "x": 137,
    "y": 407
  },
  "hasClickThrough": false,
  "isFlippedHorizontal": false,
  "isFlippedVertical": false,
  "isLocked": false,
  "isVisible": true,
  "layerListExpandedType": 0,
  "layers": [
    {
      "class": "text",
      "id": "DD257633-64B0-4AEF-B576-BF3056831098"
    },
    {
      "class": "group",
      "id": "BDE11160-7409-402F-8F74-269DCECA1A93"
    }
  ],
  "name": "Group 3",
  "nameIsFixed": false,
  "originalObjectID": "477A84F2-CBF3-443B-A824-6C16811267A7",
  "resizingConstraint": 54,
  "resizingType": 0,
  "rotation": 0,
  "shouldBreakMaskChain": false,
  "style": {
    "_class": "style",
    "endDecorationType": 0,
    "miterLimit": 10,
    "startDecorationType": 0
  },
  "userInfo": {
    "com.animaapp.stc-sketch-plugin": {
      "kModelPropertiesKey": {
      }
    }
  }
}